{
  "schema": "aegis.er-golden/v1",
  "description": "Fictional T26 ER golden set: cross-script variants, hard negatives, common names, missing corroborating fields, and deterministic background mentions.",
  "mentions": [
    {"id":"nimal_latin","truth_entity":"person_nimal","record":"record_nimal_latin","name":"Nimal Perera","aliases":["Mali"],"affiliations":["Harbor Mutual Society"],"date_of_birth":"1990-06-15","identifiers":[{"predicate":"has_nic","value":"FIXTURE-ID-NIMAL-01","jurisdiction":"DEMO"}]},
    {"id":"nimal_sinhala","truth_entity":"person_nimal","record":"record_nimal_sinhala","name":"නිමල් පෙරේරා","aliases":["Mali"],"affiliations":["Harbor Mutual Society"],"date_of_birth":"1990-06-15","identifiers":[{"predicate":"has_nic","value":"fixture-id-nimal-01","jurisdiction":"DEMO"}]},
    {"id":"mohamed_variant_a","truth_entity":"person_mohamed","record":"record_mohamed_a","name":"Mohamed Rizvi","aliases":["Riz"],"affiliations":["Lagoon Reading Circle"],"date_of_birth":"1987-11-04"},
    {"id":"mohamed_variant_b","truth_entity":"person_mohamed","record":"record_mohamed_b","name":"Mohammed Risvi","aliases":["Riz"],"affiliations":["Lagoon Reading Circle"],"date_of_birth":"1987-11-04"},
    {"id":"ruwan_north","truth_entity":"person_ruwan_north","record":"record_ruwan_north","name":"Ruwan Silva","aliases":["Ruwan North"],"date_of_birth":"1984-03-12"},
    {"id":"ruwan_south","truth_entity":"person_ruwan_south","record":"record_ruwan_south","name":"Ruwan Silva","aliases":["Ruwan South"],"date_of_birth":"1992-10-08"},

    {"id":"bg_01","truth_entity":"background_01","record":"background_record_01","name":"Abar Quillon"},
    {"id":"bg_02","truth_entity":"background_02","record":"background_record_02","name":"Bexi Ravorn"},
    {"id":"bg_03","truth_entity":"background_03","record":"background_record_03","name":"Cudal Sefrin"},
    {"id":"bg_04","truth_entity":"background_04","record":"background_record_04","name":"Dovin Talgor"},
    {"id":"bg_05","truth_entity":"background_05","record":"background_record_05","name":"Eram Ulden"},
    {"id":"bg_06","truth_entity":"background_06","record":"background_record_06","name":"Feska Vorin"},
    {"id":"bg_07","truth_entity":"background_07","record":"background_record_07","name":"Gabin Wexler"},
    {"id":"bg_08","truth_entity":"background_08","record":"background_record_08","name":"Hodar Xemil"},
    {"id":"bg_09","truth_entity":"background_09","record":"background_record_09","name":"Ivena Yordel"},
    {"id":"bg_10","truth_entity":"background_10","record":"background_record_10","name":"Jorun Zafri"},
    {"id":"bg_11","truth_entity":"background_11","record":"background_record_11","name":"Kelis Bront"},
    {"id":"bg_12","truth_entity":"background_12","record":"background_record_12","name":"Lomar Cevik"},
    {"id":"bg_13","truth_entity":"background_13","record":"background_record_13","name":"Mavik Dorel"},
    {"id":"bg_14","truth_entity":"background_14","record":"background_record_14","name":"Nesra Fulin"},
    {"id":"bg_15","truth_entity":"background_15","record":"background_record_15","name":"Odran Gavel"},
    {"id":"bg_16","truth_entity":"background_16","record":"background_record_16","name":"Pexal Hurin"},
    {"id":"bg_17","truth_entity":"background_17","record":"background_record_17","name":"Qorin Javel"},
    {"id":"bg_18","truth_entity":"background_18","record":"background_record_18","name":"Radel Kimon"},
    {"id":"bg_19","truth_entity":"background_19","record":"background_record_19","name":"Suvik Leron"},
    {"id":"bg_20","truth_entity":"background_20","record":"background_record_20","name":"Tebar Moxin"},
    {"id":"bg_21","truth_entity":"background_21","record":"background_record_21","name":"Ufras Nodil"},
    {"id":"bg_22","truth_entity":"background_22","record":"background_record_22","name":"Vekor Pavin"},
    {"id":"bg_23","truth_entity":"background_23","record":"background_record_23","name":"Wadim Qorel"},
    {"id":"bg_24","truth_entity":"background_24","record":"background_record_24","name":"Xeran Ruvik"},
    {"id":"bg_25","truth_entity":"background_25","record":"background_record_25","name":"Yolin Sarem"},
    {"id":"bg_26","truth_entity":"background_26","record":"background_record_26","name":"Zukar Tovin"},
    {"id":"bg_27","truth_entity":"background_27","record":"background_record_27","name":"Bralo Uxen"},
    {"id":"bg_28","truth_entity":"background_28","record":"background_record_28","name":"Crevi Vador"},
    {"id":"bg_29","truth_entity":"background_29","record":"background_record_29","name":"Drano Wulic"},
    {"id":"bg_30","truth_entity":"background_30","record":"background_record_30","name":"Flori Xavin"},
    {"id":"bg_31","truth_entity":"background_31","record":"background_record_31","name":"Gruma Yelis"},
    {"id":"bg_32","truth_entity":"background_32","record":"background_record_32","name":"Hesko Zorin"},
    {"id":"bg_33","truth_entity":"background_33","record":"background_record_33","name":"Javil Buren"},
    {"id":"bg_34","truth_entity":"background_34","record":"background_record_34","name":"Klena Cavor"},
    {"id":"bg_35","truth_entity":"background_35","record":"background_record_35","name":"Prudi Dexon"},
    {"id":"bg_36","truth_entity":"background_36","record":"background_record_36","name":"Skaro Evin"},
    {"id":"bg_37","truth_entity":"background_37","record":"background_record_37","name":"Trena Fozil"},
    {"id":"bg_38","truth_entity":"background_38","record":"background_record_38","name":"Vrona Gexar"},
    {"id":"bg_39","truth_entity":"background_39","record":"background_record_39","name":"Wexi Hador"},
    {"id":"bg_40","truth_entity":"background_40","record":"background_record_40","name":"Xolam Iver"},
    {"id":"bg_41","truth_entity":"background_41","record":"background_record_41","name":"Yuric Jemon"},
    {"id":"bg_42","truth_entity":"background_42","record":"background_record_42","name":"Zefra Kudin"},
    {"id":"bg_43","truth_entity":"background_43","record":"background_record_43","name":"Bovin Lexar"},
    {"id":"bg_44","truth_entity":"background_44","record":"background_record_44","name":"Cemra Muvin"},
    {"id":"bg_45","truth_entity":"background_45","record":"background_record_45","name":"Daxil Norum"},
    {"id":"bg_46","truth_entity":"background_46","record":"background_record_46","name":"Evor Pexin"},
    {"id":"bg_47","truth_entity":"background_47","record":"background_record_47","name":"Fulin Qamar"},
    {"id":"bg_48","truth_entity":"background_48","record":"background_record_48","name":"Goran Rixel"},
    {"id":"bg_49","truth_entity":"background_49","record":"background_record_49","name":"Huxel Sovar"},
    {"id":"bg_50","truth_entity":"background_50","record":"background_record_50","name":"Ibram Turel"},
    {"id":"bg_51","truth_entity":"background_51","record":"background_record_51","name":"Jexon Uvali"},
    {"id":"bg_52","truth_entity":"background_52","record":"background_record_52","name":"Kavor Vexim"},
    {"id":"bg_53","truth_entity":"background_53","record":"background_record_53","name":"Lurin Wazol"},
    {"id":"bg_54","truth_entity":"background_54","record":"background_record_54","name":"Moxel Xurin"}
  ],
  "transliteration_pairs": [
    {"left":"nimal_latin","right":"nimal_sinhala"},
    {"left":"mohamed_variant_a","right":"mohamed_variant_b"}
  ],
  "distinct_pairs": [
    {"left":"ruwan_north","right":"ruwan_south"}
  ]
}
